{
  "관리대지위치관리번호": {
    "표현형식": "11680-10002997001",
    "정규식": null,
    "예시": null,
    "설명": "대지위치 데이터셋의 식별자로 시군구코드-해당 지방자치단체내 식별자\"로 구성 * 해당 지방자치단체내 식별자 : 해당 지방자치단체의 세움터 시스템에서 부여한 식별자 \"",
    "필수여부": "필수",
    "허용값": null
  },
  "관리허가대장관리번호": {
    "표현형식": "11680-10002754501",
    "정규식": null,
    "예시": null,
    "설명": "기본정보(기본개요) 데이터셋의 식별자로 시군구코드 - 해당 지방자치단체내 식별자\"로 구성 * 해당 지방자치단체내 식별자 : 해당 지방자치단체의 세움터 시스템에서 부여한 식별자 * 주동구분코드가 '0'(전체)이면 필수 \"",
    "필수여부": "선택",
    "허용값": null
  },
  "관리동별개요관리번호": {
    "표현형식": "11680-10003393901",
    "정규식": null,
    "예시": null,
    "설명": "동별개요 데이터셋의 식별자로 시군구코드 - 해당 지방자치단체내 식별자\"로 구성 * 해당 지방자치단체내 식별자 : 해당 지방자치단체의 세움터 시스템에서 부여한 식별자 * 주동구분코드가 '1'(동별)이면 필수 \"",
    "필수여부": "선택",
    "허용값": null
  },
  "대지위치": {
    "표현형식": "<예시1:본번만있는경우> 서울특별시강남구개포동12번지  <예시2:본번,지번이있는경우> 서울특별시강남구개포동12-7번지",
    "정규식": ".*(동|읍|면)\\s*\\d+(-\\d+)?(번지)?",
    "예시": null,
    "설명": "대지의 상세지번주소 * 지번본번과 지번부번의 숫자가 '0' 으로 시작되는경우 '0'은 표시하지 않음",
    "필수여부": "필수",
    "허용값": null
  },
  "시군구코드": {
    "표현형식": "11680",
    "정규식": null,
    "예시": null,
    "설명": "법률로 지정된 시도/시군구의 하부 행정구역 단위인 법정동에 부여된 행정표준코드인 법정동코드 중 시도 및 시군구를 구분하는 상위 5자리 * 행정표준코드사용 : 법정동코드 행정표준코드관리시스템(code.go.kr)에서 조회 가능 * 법정동(법정리) 체계는 1910년 실시한 토지조사사업에 바탕을 둔것으로 정부기관의 모든문서나 재산권 및 각종 권리행사 등 법률행위때 이용되는 법정 땅이름",
    "필수여부": "필수",
    "허용값": null
  },
  "법정동코드": {
    "표현형식": "10300",
    "정규식": null,
    "예시": null,
    "설명": "법률로 지정된 시·도/시군구의 하부 행정구역 단위인 법정동에 부여된 행정표준코드인 법정동코드 중 읍면동 및 리를 구분하는 하위 5자리 * 행정표준코드사용 : 법정동코드 행정표준코드관리시스템(code.go.kr)에서 조회 가능 * 법정동(법정리) 체계는 1910년 실시한 토지조사사업에 바탕을 둔것으로 정부기관의 모든문서나 재산권 및 각종 권리행사 등 법률행위때 이용되는 법정 땅이름",
    "필수여부": "필수",
    "허용값": null
  },
  "대지구분코드": {
    "표현형식": "1",
    "정규식": null,
    "예시": null,
    "설명": "대지에 대한 구분코드 * 행정표준코드사용 : 지번표시유형코드",
    "필수여부": "필수",
    "허용값": [
      "0",
      "1",
      "2"      
    ]
  },
  "번": {
    "표현형식": "12",
    "정규식": null,
    "예시": null,
    "설명": "필지에 부여하여 지적공부에 등록한 번호인 지번의 본번 * 해당사항 없을 시 '0000'",
    "필수여부": "필수",
    "허용값": null
  },
  "지": {
    "표현형식": "0",
    "정규식": null,
    "예시": null,
    "설명": "필지에 부여하여 지적공부에 등록한 번호인 지번의 부번 * 해당사항 없을 시 '0000'",
    "필수여부": "필수",
    "허용값": null
  },
  "대표구분코드": {
    "표현형식": "1",
    "정규식": null,
    "예시": null,
    "설명": "해당 대지가 여러 필지로 구성되어 있을 경우 해당 대지위치가 대표위치인지 구분하는 코드",
    "필수여부": "필수",
    "허용값": [
      "0",
      "1"
    ]
  },
  "주동구분코드": {
    "표현형식": "0",
    "정규식": null,
    "예시": null,
    "설명": "주동 구분 코드 * “주동”이라 함은 하나의 코아를 사용하는 독립된 공동주택을 말함",
    "필수여부": "필수",
    "허용값": [
      "0",
      "1"
    ]
  },
  "주동구분명": {
    "표현형식": "전체",
    "정규식": null,
    "예시": null,
    "설명": "주동구분 명칭 * API서비스 제공 시 본 항목 생략 가능",
    "필수여부": "필수",
    "허용값": [
      "전체",
      "동별"
    ]
  },
  "행정동코드": {
    "표현형식": "660",
    "정규식": null,
    "예시": null,
    "설명": "행정기관코드 10자리 중 6,7,8번의 3자리 * 행정동 : 행정능률과 주민편의를 위하여 당해 지방자치단체의 조례가 정하는 바에 의하여 하나의 동·리를 2개 이상의 동·리로 운영하거나 2개 이상의 동·리를 하나의 동·리로 운영하는 등 행정운영상 따로 둔 동·리 * 행정기관코드는 행정안전부홈페이지를 통해 변경 시마다 공지됨",
    "필수여부": "선택",
    "허용값": null
  },
  "특수지명": {
    "표현형식": "서울강남보금자리 택지개발지구",
    "정규식": null,
    "예시": null,
    "설명": "특수지의 명칭 * 특수지 : 토지용도가 특수하고 거래사례가 희소하여 시장가치의 측정이 어려운 토지",
    "필수여부": "선택",
    "허용값": null
  },
  "블록": {
    "표현형식": "2",
    "정규식": null,
    "예시": null,
    "설명": "블록에 부여된 번호 * 블록 : 토지구획정리사업이나, 택지개발사업 등으로 조성된 대지를 구획하는 단위로 양 4방이 도로에 의해 단절된 최소 단위의 구역",
    "필수여부": "선택",
    "허용값": null
  },
  "로트": {
    "표현형식": "2101",
    "정규식": null,
    "예시": null,
    "설명": "로트에 부여된 번호 * 로트 : 토지구획정리사업이나, 택지개발사업 등으로 조성된 대지를 구획하는 단위로 하나의 블록내에 도로에 면하여 최소 단위로 구획된 하나의 토지",
    "필수여부": "선택",
    "허용값": null
  },
  "지목코드": {
    "표현형식": "1",
    "정규식": null,
    "예시": null,
    "설명": "주된 용도에 따라 땅을 구분하는 명목에 부여한 코드 * 참고법률 : 「공간정보의 구축 및 관리 등에 관한 법률」 제67조에 따른 구분 ※행정표준코드사용 : 지목코드",
    "필수여부": "필수",
    "허용값": null
  },
  "지목명": {
    "표현형식": "전",
    "정규식": null,
    "예시": null,
    "설명": "지목코드의 명칭 ※행정표준코드사용 : 지목코드 * API서비스 제공 시 본 항목 생략 가능",
    "필수여부": "필수",
    "허용값": null
  },
  "관련지번명": {
    "표현형식": "473-3,472-8,474-2,607-8",
    "정규식": null,
    "예시": null,
    "설명": "둘 이상의 필지를 하나의 대지로 하여 건축물이 있는 경우 주 지번 이외의 지번",
    "필수여부": "선택",
    "허용값": null
  },
  "생성일자": {
    "표현형식": "2014-03-07",
    "정규식": null,
    "예시": null,
    "설명": "시군구의 건축행정정보가 취합되어 적재된 일자",
    "필수여부": "필수",
    "허용값": null
  }
}